Metadata-Version: 1.0
Name: mosaiq-transfer-check
Version: 0.2.0
Summary: Compare mosaiq entries for two different sites.
Home-page: UNKNOWN
Author: Simon Biggs
Author-email: mail@simonbiggs.net
License: AGPL3+
Platform: UNKNOWN
